Metadata-Version: 1.0
Name: scrapy-ssdb
Version: 0.0.1
Summary: scrapy and ssdb
Home-page: https://github.com/huahhh
Author: besttime
Author-email: 1007897126@qq.com
License: MIT License
Keywords: scrapy,ssdb
Platform: any
